vmtreport/__about__.py
vmtreport/__init__.py
vmtreport/actions.py
vmtreport/command_line.py
vmtreport/common.py
vmtreport/stats.py
vmtreport/targets.py
vmtreport/util.py
vmtreport-2.1.0.dist-info/LICENSE
vmtreport-2.1.0.dist-info/METADATA
vmtreport-2.1.0.dist-info/WHEEL
vmtreport-2.1.0.dist-info/entry_points.txt
vmtreport-2.1.0.dist-info/top_level.txt
vmtreport-2.1.0.dist-info/RECORD
