Metadata-Version: 2.1
Name: vmtreport
Version: 2.1.0
Summary: Turbonomic Report Interface
Home-page: https://github.com/rastern/vmt-report
Author: R.A. Stern
Author-email: richard.stern@turbonomic.com
License: Apache 2.0
Platform: UNKNOWN
Classifier: Intended Audience :: Developers
Classifier: License :: OSI Approved :: Apache Software License
Classifier: Operating System :: OS Independent
Classifier: Programming Language :: Python :: 3
Classifier: Topic :: Software Development
Requires-Python: >=3.7
License-File: LICENSE
Requires-Dist: requests (>=2.21.0)
Requires-Dist: vmtconnect (>=3.6.1)
Requires-Dist: arbiter (>=1.1.0)
